anilibria/__init__.py
anilibria/const.py
anilibria/api/__init__.py
anilibria/api/dispatch.py
anilibria/api/error.py
anilibria/api/gateway/__init__.py
anilibria/api/gateway/client.py
anilibria/api/gateway/events/__init__.py
anilibria/api/gateway/events/anilibria.py
anilibria/api/gateway/events/base.py
anilibria/api/gateway/events/internal.py
anilibria/api/http/__init__.py
anilibria/api/http/client.py
anilibria/api/http/public.py
anilibria/api/http/request.py
anilibria/api/http/route.py
anilibria/api/models/__init__.py
anilibria/api/models/attrs_utils.py
anilibria/api/models/cattrs_utils.py
anilibria/api/models/enums.py
anilibria/api/models/misc.py
anilibria/api/models/title.py
anilibria/client/__init__.py
anilibria/client/client.py
anilibria/utils/__init__.py
anilibria/utils/serializer.py
anilibria/utils/typings.py
anilibria.py-1.0.4.dist-info/LICENSE
anilibria.py-1.0.4.dist-info/METADATA
anilibria.py-1.0.4.dist-info/WHEEL
anilibria.py-1.0.4.dist-info/top_level.txt
anilibria.py-1.0.4.dist-info/RECORD
