Metadata-Version: 2.1
Name: anilibria.py
Version: 1.0.4
Summary: An async API wrapper for the anilibria.tv
Home-page: https://github.com/Damego/anilibria.py
Author: Damego
Author-email: danyabatueff@gmail.com
License: GPL-3.0 License
Classifier: Intended Audience :: Developers
Classifier: License :: OSI Approved :: MIT License
Classifier: Natural Language :: English
Classifier: Operating System :: OS Independent
Classifier: Programming Language :: Python :: 3
Classifier: Programming Language :: Python :: 3.10
Classifier: Programming Language :: Python :: 3.11
Classifier: Topic :: Internet
Classifier: Topic :: Software Development :: Libraries :: Python Modules
Classifier: Topic :: Software Development :: Libraries
Classifier: Topic :: Utilities
Classifier: Typing :: Typed
Requires-Python: >=3.10
License-File: LICENSE
Requires-Dist: aiohttp >=3.8.3
Requires-Dist: attrs ==22.2.0
Requires-Dist: cattrs ==22.2.0
Requires-Dist: orjson ==3.8.5
Requires-Dist: tomli ==2.0.1
Provides-Extra: readthedocs
Requires-Dist: furo ; extra == 'readthedocs'
Requires-Dist: readthedocs-sphinx-search ; extra == 'readthedocs'
Requires-Dist: Sphinx ; extra == 'readthedocs'
Requires-Dist: sphinx-hoverxref ; extra == 'readthedocs'
